dakora_instrumentation/__init__.py
dakora_instrumentation/generic.py
dakora_instrumentation/py.typed
dakora_instrumentation/_internal/__init__.py
dakora_instrumentation/_internal/exporter.py
dakora_instrumentation/_internal/processors.py
dakora_instrumentation/_internal/setup.py
dakora_instrumentation/_internal/utils.py
dakora_instrumentation/frameworks/__init__.py
dakora_instrumentation/frameworks/maf/__init__.py
dakora_instrumentation/frameworks/maf/integration.py
dakora_instrumentation/frameworks/maf/middleware.py
dakora_instrumentation/providers/__init__.py
dakora_instrumentation/providers/anthropic/__init__.py
dakora_instrumentation/providers/openai/__init__.py
dakora_instrumentation-0.2.0.dist-info/METADATA
dakora_instrumentation-0.2.0.dist-info/WHEEL
dakora_instrumentation-0.2.0.dist-info/licenses/LICENSE
dakora_instrumentation-0.2.0.dist-info/RECORD
