Metadata-Version: 2.4
Name: dakora-instrumentation
Version: 0.2.0
Summary: OpenTelemetry instrumentation for LLM applications with Dakora observability
Project-URL: Homepage, https://github.com/dakora-labs/dakora
Project-URL: Repository, https://github.com/dakora-labs/dakora.git
Project-URL: Issues, https://github.com/dakora-labs/dakora/issues
Author-email: Dakora Labs <support@dakora.io>
License:                                  Apache License
License-File: LICENSE
Keywords: agents,ai,instrumentation,llm,observability,opentelemetry,telemetry,tracing
Classifier: Development Status :: 4 - Beta
Classifier: Intended Audience :: Developers
Classifier: License :: OSI Approved :: Apache Software License
Classifier: Programming Language :: Python :: 3
Classifier: Programming Language :: Python :: 3.11
Classifier: Programming Language :: Python :: 3.12
Classifier: Programming Language :: Python :: 3.13
Classifier: Topic :: Software Development :: Libraries :: Python Modules
Classifier: Topic :: System :: Monitoring
Classifier: Typing :: Typed
Requires-Python: >=3.11
Requires-Dist: dakora~=0.2.0
Requires-Dist: packaging>=21.0
Provides-Extra: maf
Requires-Dist: agent-framework-core>=1.0.0b251016; extra == 'maf'
Requires-Dist: opentelemetry-exporter-otlp-proto-http>=1.24.0; extra == 'maf'
